.travis.yml
AUTHORS
LICENSE
README.rst
circle.yml
requirements.txt
setup.cfg
setup.py
test-requirements.txt
tox.ini
spec/KoreanNormalizerTest.py
spec/__init__.py
twitter_korean/__init__.py
twitter_korean/_setup_hooks.py
twitter_korean.egg-info/PKG-INFO
twitter_korean.egg-info/SOURCES.txt
twitter_korean.egg-info/dependency_links.txt
twitter_korean.egg-info/not-zip-safe
twitter_korean.egg-info/pbr.json
twitter_korean.egg-info/requires.txt
twitter_korean.egg-info/top_level.txt
twitter_korean/normalizer/KoreanNormalizer.py
twitter_korean/normalizer/__init__.py
twitter_korean/util/KoreanDictionaryProvider.py
twitter_korean/util/KoreanPos.py
twitter_korean/util/__init__.py