Metadata-Version: 1.1
Name: twitter-korean
Version: 0.1.0.dev527
Summary: Python port to the normalizer in https://github.com/twitter/twitter-korean-text
Home-page: https://github.com/cedar101/twitter_korean-py
Author: Baeg-il Kim
Author-email: cedar101@gmail.com
License: UNKNOWN
Keywords: twkorean
Platform: UNKNOWN
Classifier: Environment :: Console
Classifier: Intended Audience :: Developers
Classifier: Intended Audience :: Science/Research
Classifier: Natural Language :: Korean
Classifier: Programming Language :: Python
Classifier: Programming Language :: Python :: 2
Classifier: Programming Language :: Python :: 2.7
Classifier: Programming Language :: Python :: 3
Classifier: Programming Language :: Python :: 3.5
Classifier: Topic :: Software Development :: Libraries :: Python Modules
Classifier: Topic :: Text Processing :: Linguistic
Classifier: Topic :: Text Processing
Classifier: Development Status :: 3 - Alpha
Classifier: License :: OSI Approved :: Apache Software License
